modalyzer/EFDD.py
modalyzer/ITD.py
modalyzer/ModeShape.py
modalyzer/PolyMAX.py
modalyzer/Preprocess.py
modalyzer/SSI.py
modalyzer/__init__.py
modalyzer-1.2.2.dist-info/METADATA
modalyzer-1.2.2.dist-info/WHEEL
modalyzer-1.2.2.dist-info/licenses/AUTHORS.md
modalyzer-1.2.2.dist-info/licenses/LICENSE
modalyzer-1.2.2.dist-info/RECORD
