Metadata-Version: 2.4
Name: modalyzer
Version: 1.2.2
Summary: Modalyzer: Operational Modal Analysis (OMA) toolkit in Python (EFDD, SSI, PolyMAX, ITD).
Project-URL: Homepage, https://github.com/MehrabNF/modalyzer-test
Project-URL: Repository, https://github.com/MehrabNF/modalyzer-test
Project-URL: Issues, https://github.com/MehrabNF/modalyzer-test/issues
Author: Modalyzer Developers
License: MIT License
License-File: AUTHORS.md
License-File: LICENSE
Classifier: Intended Audience :: Science/Research
Classifier: License :: OSI Approved :: MIT License
Classifier: Operating System :: OS Independent
Classifier: Programming Language :: Python :: 3
Classifier: Programming Language :: Python :: 3 :: Only
Classifier: Programming Language :: Python :: 3.9
Classifier: Programming Language :: Python :: 3.10
Classifier: Topic :: Scientific/Engineering
Requires-Python: >=3.9
Requires-Dist: matplotlib<3.10,>=3.9; python_version < '3.10'
Requires-Dist: matplotlib<4,>=3.9; python_version >= '3.10'
Requires-Dist: nbformat>=4.2.0
Requires-Dist: numpy<3,>=2.0
Requires-Dist: pandas<3,>=2.3
Requires-Dist: plotly<7,>=6.3
Requires-Dist: scipy<2,>=1.13
Requires-Dist: torch<2.9,>=2.8; python_version < '3.10'
Requires-Dist: torch<3,>=2.8; python_version >= '3.10'
Provides-Extra: dev
Requires-Dist: black>=24; extra == 'dev'
Requires-Dist: build>=1.2.1; extra == 'dev'
Requires-Dist: pre-commit>=3.7; extra == 'dev'
Requires-Dist: pytest-cov>=5; extra == 'dev'
Requires-Dist: pytest>=8; extra == 'dev'
Requires-Dist: ruff>=0.5; extra == 'dev'
Requires-Dist: twine>=5.1.1; extra == 'dev'
Provides-Extra: notebook
Requires-Dist: ipykernel>=6; extra == 'notebook'
